rethinkdb_mock/__init__.py
rethinkdb_mock/ast.py
rethinkdb_mock/ast_base.py
rethinkdb_mock/db.py
rethinkdb_mock/joins.py
rethinkdb_mock/rql_rewrite.py
rethinkdb_mock/rtime.py
rethinkdb_mock/scope.py
rethinkdb_mock/util.py
rethinkdb_mock-0.10.1.dist-info/LICENSE
rethinkdb_mock-0.10.1.dist-info/METADATA
rethinkdb_mock-0.10.1.dist-info/WHEEL
rethinkdb_mock-0.10.1.dist-info/top_level.txt
rethinkdb_mock-0.10.1.dist-info/zip-safe
rethinkdb_mock-0.10.1.dist-info/RECORD
