Metadata-Version: 2.1
Name: rethinkdb-mock
Version: 0.10.1
Summary: A pure-python in-memory mock of rethinkdb (formerly MockThink)
Home-page: https://github.com/Inveracity/rethinkdb-mock
Maintainer: Christopher Baklid
Maintainer-email: cbaklid@gmail.com
License: UNKNOWN
Platform: UNKNOWN
Classifier: License :: OSI Approved :: MIT License
Classifier: Operating System :: OS Independent
Classifier: Programming Language :: Python
Classifier: Programming Language :: Python :: 3.7
Classifier: Programming Language :: Python :: 3.8
Classifier: Programming Language :: Python :: 3.9
Classifier: Topic :: Database
Classifier: Topic :: Software Development :: Testing :: Mocking
Requires-Python: >=3.7
License-File: LICENSE
Requires-Dist: rethinkdb (>=2.4.8)
Requires-Dist: python-dateutil
Requires-Dist: future
